pxgpt/__init__.py
pxgpt/__main__.py
pxgpt/chat.py
pxgpt/cli.py
pxgpt/config.py
pxgpt/docs.py
pxgpt/frontend/build/assets/favicon.png
pxgpt/frontend/build/assets/index.css
pxgpt/frontend/build/assets/index.js
pxgpt/frontend/build/index.html
pxgpt/ingest.py
pxgpt/logger.py
pxgpt/manager.py
pxgpt/rings/__init__.py
pxgpt/rings/_callbacks.py
pxgpt/rings/_llms.py
pxgpt/rings/_mixins.py
pxgpt/rings/base.py
pxgpt/rings/chatopenai.py
pxgpt/rings/gpt4all.py
pxgpt/rings/llamacpp.py
pxgpt/rings/openai.py
pxgpt/serve.py
pxgpt/version.py
pxgpt/ws.py
pxgpt/zzz.py
pxgpt-0.0.1.dist-info/LICENSE
pxgpt-0.0.1.dist-info/METADATA
pxgpt-0.0.1.dist-info/WHEEL
pxgpt-0.0.1.dist-info/entry_points.txt
pxgpt-0.0.1.dist-info/RECORD
