Metadata-Version: 2.1
Name: pxgpt
Version: 0.0.1
Summary: Your personal, powerful and private GPT.
License: Apache-2.0
Author: pwwang
Author-email: pwwang@pwwang.com
Requires-Python: >=3.9,<4.0
Classifier: License :: OSI Approved :: Apache Software License
Classifier: Programming Language :: Python :: 3
Classifier: Programming Language :: Python :: 3.9
Classifier: Programming Language :: Python :: 3.10
Classifier: Programming Language :: Python :: 3.11
Provides-Extra: all
Provides-Extra: gpt4all
Provides-Extra: llama-cpp
Provides-Extra: openai
Requires-Dist: argx (>=0.2.9,<0.3.0)
Requires-Dist: faiss-cpu (>=1.7.4,<2.0.0)
Requires-Dist: gpt4all (>=1.0.3,<2.0.0) ; extra == "gpt4all" or extra == "all"
Requires-Dist: langchain (>=0.0.234,<0.0.235)
Requires-Dist: llama-cpp-python (>=0.1.70,<0.2.0) ; extra == "llama-cpp" or extra == "all"
Requires-Dist: openai (>=0.27.8,<0.28.0) ; extra == "openai" or extra == "all"
Requires-Dist: pandas (>=2.0.3,<3.0.0)
Requires-Dist: prompt-toolkit (>=3.0.39,<4.0.0)
Requires-Dist: py (>=1.11.0,<2.0.0)
Requires-Dist: pyarrow (>=12.0.1,<13.0.0)
Requires-Dist: pymupdf (>=1.22.5,<2.0.0)
Requires-Dist: python-simpleconf[yaml] (>=0.6.0,<0.7.0)
Requires-Dist: quart (>=0.18.4,<0.19.0)
Requires-Dist: scikit-learn (>=1.3.0,<2.0.0)
Requires-Dist: tiktoken (>=0.4.0,<0.5.0) ; extra == "openai"
